README.rst
setup.py
microhttp_ratelimit/__init__.py
microhttp_ratelimit/exceptions.py
microhttp_ratelimit/extension.py
microhttp_ratelimit/leaky_bucket.py
microhttp_ratelimit.egg-info/PKG-INFO
microhttp_ratelimit.egg-info/SOURCES.txt
microhttp_ratelimit.egg-info/dependency_links.txt
microhttp_ratelimit.egg-info/not-zip-safe
microhttp_ratelimit.egg-info/requires.txt
microhttp_ratelimit.egg-info/top_level.txt