Metadata-Version: 1.1
Name: microhttp-ratelimit
Version: 0.1.0
Summary: Rate limit extension for microhttp
Home-page: UNKNOWN
Author: Mahdi Ghane.g
Author-email: UNKNOWN
License: MIT License
Platform: UNKNOWN
Classifier: Environment :: Console
Classifier: Environment :: Web Environment
Classifier: Intended Audience :: Developers
Classifier: Natural Language :: English
Classifier: Development Status :: 3 - Alpha
Classifier: License :: OSI Approved :: MIT License
Classifier: Operating System :: OS Independent
Classifier: Programming Language :: Python :: 3.6
Classifier: Topic :: Software Development
Classifier: Topic :: Software Development :: Libraries
Classifier: Topic :: Software Development :: Libraries :: Python Modules
